drca/__init__.py
drca/drca.py
drca-0.8.0.dist-info/LICENSE
drca-0.8.0.dist-info/METADATA
drca-0.8.0.dist-info/WHEEL
drca-0.8.0.dist-info/top_level.txt
drca-0.8.0.dist-info/RECORD
